{"code":"0000","message":"成功","data":{"item":[{"address":"河北省保定市恒祥北大街3188号","admissions":2,"answerurl":"https://answer.eol.cn/fillmess/index?id=1215\u0026source=zsgk_app","belong":"河北省","central":2,"city_id":1306,"city_name":"保定市","code_enroll":1142000,"colleges_level":"","county_id":0,"county_name":"","department":2,"doublehigh":0,"dual_class":38003,"dual_class_name":"","f211":2,"f985":2,"id":"gkschool692","is_recruitment":1,"is_top":2,"level":2001,"level_name":"普通本科","name":"河北金融学院","nature":36000,"nature_name":"公办","province_id":13,"province_name":"河北","rank":400,"rank_type":38,"school_id":692,"school_type":6000,"single_province":"","special":[],"type":5006,"type_name":"财经类","view_month":"14.3w","view_month_number":143037,"view_total":"363.4w","view_total_number":3634186,"view_week":"3.9w","view_week_number":38703,"view_year":393576},{"address":"江西省南昌市高新技术开发区天祥大道289号","admissions":2,"answerurl":"https://m-view.eol.cn/h5/zsgk/answer_noresult.html?t=1111","belong":"江西省","central":2,"city_id":3601,"city_name":"南昌市","code_enroll":1131900,"colleges_level":"","county_id":360111,"county_name":"青山湖区","department":2,"doublehigh":0,"dual_class":38003,"dual_class_name":"","f211":2,"f985":2,"id":"gkschool867","is_recruitment":1,"is_top":2,"level":2001,"level_name":"普通本科","name":"南昌工程学院","nature":36000,"nature_name":"公办","province_id":36,"province_name":"江西","rank":401,"rank_type":140,"school_id":867,"school_type":6000,"single_province":"","special":[],"type":5001,"type_name":"理工类","view_month":"20.5w","view_month_number":205050,"view_total":"363w","view_total_number":3629828,"view_week":"6.1w","view_week_number":61467,"view_year":686901},{"address":"河南省平顶山市新城区龙翔大道","admissions":2,"answerurl":"https://answer.eol.cn/fillmess/index?id=1846\u0026source=zsgk_app","belong":"河南省","central":2,"city_id":4104,"city_name":"平顶山市","code_enroll":1176500,"colleges_level":"","county_id":0,"county_name":"","department":2,"doublehigh":0,"dual_class":38003,"dual_class_name":"","f211":2,"f985":2,"id":"gkschool1518","is_recruitment":1,"is_top":2,"level":2001,"level_name":"普通本科","name":"河南城建学院","nature":36000,"nature_name":"公办","province_id":41,"province_name":"河南","rank":402,"rank_type":141,"school_id":1518,"school_type":6000,"single_province":"","special":[],"type":5001,"type_name":"理工类","view_month":"15.3w","view_month_number":152937,"view_total":"361.4w","view_total_number":3614440,"view_week":"5.1w","view_week_number":51117,"view_year":735699},{"address":"贵州省贵安新区大学城贵州医科大学","admissions":2,"answerurl":"https://answer.eol.cn/fillmess/index?id=1065\u0026source=zsgk_app","belong":"贵州省","central":2,"city_id":5201,"city_name":"贵阳市","code_enroll":1066000,"colleges_level":"","county_id":0,"county_name":"","department":2,"doublehigh":0,"dual_class":38003,"dual_class_name":"","f211":2,"f985":2,"id":"gkschool515","is_recruitment":1,"is_top":2,"level":2001,"level_name":"普通本科","name":"贵州医科大学","nature":36000,"nature_name":"公办","province_id":52,"province_name":"贵州","rank":403,"rank_type":33,"school_id":515,"school_type":6000,"single_province":"","special":[],"type":5003,"type_name":"医药类","view_month":"19.5w","view_month_number":194646,"view_total":"361w","view_total_number":3610350,"view_week":"4.9w","view_week_number":48891,"view_year":818802},{"address":"校本部驻地为湖南省郴州市郴州大道889号;王仙校区（郴州市郴州大道889号）;北湖校区（郴州市北湖区人民西路25号）","admissions":2,"answerurl":"https://answer.eol.cn/fillmess/index?id=962\u0026source=zsgk_app","belong":"湖南省","central":2,"city_id":4310,"city_name":"郴州市","code_enroll":1054500,"colleges_level":"","county_id":431003,"county_name":"苏仙区","department":2,"doublehigh":0,"dual_class":38003,"dual_class_name":"","f211":2,"f985":2,"id":"gkschool403","is_recruitment":1,"is_top":2,"level":2001,"level_name":"普通本科","name":"湘南学院","nature":36000,"nature_name":"公办","province_id":43,"province_name":"湖南","rank":404,"rank_type":112,"school_id":403,"school_type":6000,"single_province":"","special":[],"type":5000,"type_name":"综合类","view_month":"13.9w","view_month_number":138801,"view_total":"359.3w","view_total_number":3593220,"view_week":"3.9w","view_week_number":39141,"view_year":612591},{"address":"高坪校区：四川省南充市高坪区东顺路55号,顺庆校区：四川省南充市顺庆区涪江路234号","admissions":2,"answerurl":"https://answer.eol.cn/fillmess/index?id=843\u0026source=zsgk_app","belong":"四川省","central":2,"city_id":5113,"city_name":"南充市","code_enroll":1063400,"colleges_level":"","county_id":511304,"county_name":"嘉陵区","department":2,"doublehigh":0,"dual_class":38003,"dual_class_name":"","f211":2,"f985":2,"id":"gkschool276","is_recruitment":1,"is_top":2,"level":2001,"level_name":"普通本科","name":"川北医学院","nature":36000,"nature_name":"公办","province_id":51,"province_name":"四川","rank":405,"rank_type":34,"school_id":276,"school_type":6000,"single_province":"","special":[],"type":5003,"type_name":"医药类","view_month":"25.9w","view_month_number":258816,"view_total":"359.2w","view_total_number":3591930,"view_week":"4.4w","view_week_number":44217,"view_year":768048},{"address":"陕西省西安市雁塔区科技六路一号","admissions":2,"answerurl":"https://m-view.eol.cn/h5/zsgk/answer_noresult.html?t=1111","belong":"陕西省","central":2,"city_id":6101,"city_name":"西安市","code_enroll":1108000,"colleges_level":"","county_id":610103,"county_name":"碑林区","department":2,"doublehigh":0,"dual_class":38003,"dual_class_name":"","f211":2,"f985":2,"id":"gkschool1043","is_recruitment":1,"is_top":2,"level":2001,"level_name":"普通本科","name":"西安文理学院","nature":36000,"nature_name":"公办","province_id":61,"province_name":"陕西","rank":406,"rank_type":39,"school_id":1043,"school_type":6000,"single_province":"","special":[],"type":5004,"type_name":"师范类","view_month":"21.2w","view_month_number":212259,"view_total":"357.1w","view_total_number":3570679,"view_week":"3.5w","view_week_number":35286,"view_year":603549},{"address":"内蒙古自治区呼和浩特市新城区爱民街49号","admissions":2,"answerurl":"https://answer.eol.cn/fillmess/index?id=1059\u0026source=zsgk_app","belong":"内蒙古自治区","central":2,"city_id":1501,"city_name":"呼和浩特市","code_enroll":1012800,"colleges_level":"","county_id":150102,"county_name":"新城区","department":2,"doublehigh":0,"dual_class":38003,"dual_class_name":"","f211":2,"f985":2,"id":"gkschool508","is_recruitment":1,"is_top":2,"level":2001,"level_name":"普通本科","name":"内蒙古工业大学","nature":36000,"nature_name":"公办","province_id":15,"province_name":"内蒙古","rank":407,"rank_type":142,"school_id":508,"school_type":6000,"single_province":"","special":[],"type":5001,"type_name":"理工类","view_month":"10.1w","view_month_number":100950,"view_total":"357w","view_total_number":3569643,"view_week":"2.2w","view_week_number":22281,"view_year":415494},{"address":"贵州省遵义市新蒲新区学府西路6号","admissions":2,"answerurl":"https://answer.eol.cn/fillmess/index?id=1067\u0026source=zsgk_app","belong":"贵州省","central":2,"city_id":5203,"city_name":"遵义市","code_enroll":1066100,"colleges_level":"","county_id":520302,"county_name":"红花岗区","department":2,"doublehigh":0,"dual_class":38003,"dual_class_name":"","f211":2,"f985":2,"id":"gkschool518","is_recruitment":1,"is_top":2,"level":2001,"level_name":"普通本科","name":"遵义医科大学","nature":36000,"nature_name":"公办","province_id":52,"province_name":"贵州","rank":408,"rank_type":35,"school_id":518,"school_type":6000,"single_province":"","special":[],"type":5003,"type_name":"医药类","view_month":"22.2w","view_month_number":222312,"view_total":"355.3w","view_total_number":3553396,"view_week":"6w","view_week_number":60288,"view_year":618609},{"address":"黑龙江省齐齐哈尔市建华区文化大街42号","admissions":2,"answerurl":"https://m-view.eol.cn/h5/zsgk/answer_noresult.html?t=1111","belong":"黑龙江省","central":2,"city_id":2302,"city_name":"齐齐哈尔市","code_enroll":1023200,"colleges_level":"","county_id":230203,"county_name":"建华区","department":2,"doublehigh":0,"dual_class":38003,"dual_class_name":"","f211":2,"f985":2,"id":"gkschool424","is_recruitment":1,"is_top":2,"level":2001,"level_name":"普通本科","name":"齐齐哈尔大学","nature":36000,"nature_name":"公办","province_id":23,"province_name":"黑龙江","rank":409,"rank_type":113,"school_id":424,"school_type":6000,"single_province":"","special":[],"type":5000,"type_name":"综合类","view_month":"14.6w","view_month_number":146190,"view_total":"355w","view_total_number":3549635,"view_week":"3.6w","view_week_number":36480,"view_year":573123},{"address":"南京市江宁区弘景大道3601号","admissions":2,"answerurl":"https://answer.eol.cn/fillmess/index?id=724\u0026source=zsgk_app","belong":"江苏省","central":2,"city_id":3201,"city_name":"南京市","code_enroll":1146000,"colleges_level":"","county_id":320115,"county_name":"江宁区","department":2,"doublehigh":0,"dual_class":38003,"dual_class_name":"","f211":2,"f985":2,"id":"gkschool147","is_recruitment":1,"is_top":2,"level":2001,"level_name":"普通本科","name":"南京晓庄学院","nature":36000,"nature_name":"公办","province_id":32,"province_name":"江苏","rank":410,"rank_type":40,"school_id":147,"school_type":6000,"single_province":"","special":[],"type":5004,"type_name":"师范类","view_month":"28.2w","view_month_number":282192,"view_total":"354.3w","view_total_number":3542590,"view_week":"6.1w","view_week_number":61338,"view_year":1039206},{"address":"四川省达州市通川区塔石路中段519号","admissions":2,"answerurl":"https://answer.eol.cn/fillmess/index?id=1314\u0026source=zsgk_app","belong":"四川省教育厅","central":2,"city_id":5117,"city_name":"达州市","code_enroll":1064400,"colleges_level":"","county_id":511702,"county_name":"通川区","department":2,"doublehigh":0,"dual_class":38003,"dual_class_name":"","f211":2,"f985":2,"id":"gkschool798","is_recruitment":1,"is_top":2,"level":2001,"level_name":"普通本科","name":"四川文理学院","nature":36000,"nature_name":"公办","province_id":51,"province_name":"四川","rank":411,"rank_type":114,"school_id":798,"school_type":6000,"single_province":"","special":[],"type":5000,"type_name":"综合类","view_month":"21.2w","view_month_number":212193,"view_total":"354.1w","view_total_number":3540577,"view_week":"4.2w","view_week_number":42273,"view_year":804732},{"address":"重庆三峡学院百安校区（重庆市万州区五桥天星路666号 ）","admissions":2,"answerurl":"https://answer.eol.cn/fillmess/index?id=769\u0026source=zsgk_app","belong":"重庆市","central":2,"city_id":5001,"city_name":"重庆市","code_enroll":1064300,"colleges_level":"","county_id":500101,"county_name":"万州区","department":2,"doublehigh":0,"dual_class":38003,"dual_class_name":"","f211":2,"f985":2,"id":"gkschool198","is_recruitment":1,"is_top":2,"level":2001,"level_name":"普通本科","name":"重庆三峡学院","nature":36000,"nature_name":"公办","province_id":50,"province_name":"重庆","rank":412,"rank_type":115,"school_id":198,"school_type":6000,"single_province":"","special":[],"type":5000,"type_name":"综合类","view_month":"22w","view_month_number":220413,"view_total":"353.3w","view_total_number":3533329,"view_week":"5.6w","view_week_number":56493,"view_year":594549},{"address":"湖南省会长沙市芙蓉区农大路一号","admissions":2,"answerurl":"https://answer.eol.cn/fillmess/index?id=952\u0026source=zsgk_app","belong":"湖南省","central":2,"city_id":4301,"city_name":"长沙市","code_enroll":1053700,"colleges_level":"","county_id":430102,"county_name":"芙蓉区","department":2,"doublehigh":0,"dual_class":38003,"dual_class_name":"","f211":2,"f985":2,"id":"gkschool392","is_recruitment":1,"is_top":2,"level":2001,"level_name":"普通本科","name":"湖南农业大学","nature":36000,"nature_name":"公办","province_id":43,"province_name":"湖南","rank":413,"rank_type":17,"school_id":392,"school_type":6000,"single_province":"","special":[],"type":5002,"type_name":"农林类","view_month":"26w","view_month_number":259683,"view_total":"353w","view_total_number":3530191,"view_week":"7w","view_week_number":70263,"view_year":328527},{"address":"北京市海淀区学院路29号","admissions":2,"answerurl":"https://answer.eol.cn/fillmess/index?id=1295\u0026source=zsgk_app","belong":"教育部","central":2,"city_id":1101,"city_name":"北京市","code_enroll":1141500,"colleges_level":"","county_id":110108,"county_name":"海淀区","department":1,"doublehigh":0,"dual_class":38000,"dual_class_name":"双一流","f211":1,"f985":2,"id":"gkschool830","is_recruitment":1,"is_top":2,"level":2001,"level_name":"普通本科","name":"中国地质大学（北京）","nature":36000,"nature_name":"公办","province_id":11,"province_name":"北京","rank":414,"rank_type":3,"school_id":830,"school_type":6000,"single_province":"","special":[],"type":5012,"type_name":"其他","view_month":"21.1w","view_month_number":211197,"view_total":"351.4w","view_total_number":3514006,"view_week":"4.5w","view_week_number":44664,"view_year":725856},{"address":"河南省安阳市弦歌大道436号","admissions":2,"answerurl":"https://answer.eol.cn/fillmess/index?id=1371\u0026source=zsgk_app","belong":"河南省","central":2,"city_id":4105,"city_name":"安阳市","code_enroll":1047900,"colleges_level":"","county_id":0,"county_name":"","department":2,"doublehigh":0,"dual_class":38003,"dual_class_name":"","f211":2,"f985":2,"id":"gkschool878","is_recruitment":1,"is_top":2,"level":2001,"level_name":"普通本科","name":"安阳师范学院","nature":36000,"nature_name":"公办","province_id":41,"province_name":"河南","rank":415,"rank_type":41,"school_id":878,"school_type":6000,"single_province":"","special":[],"type":5004,"type_name":"师范类","view_month":"20.4w","view_month_number":203862,"view_total":"349.7w","view_total_number":3497386,"view_week":"6.1w","view_week_number":60987,"view_year":437070},{"address":"松山湖校区： 广东省东莞市松山湖大学路1号;莞城校区： 广东省东莞市莞城街道学院路251号","admissions":2,"answerurl":"https://answer.eol.cn/fillmess/index?id=858\u0026source=zsgk_app","belong":"广东省","central":2,"city_id":4419,"city_name":"东莞市","code_enroll":1181900,"colleges_level":"","county_id":0,"county_name":"","department":2,"doublehigh":0,"dual_class":38003,"dual_class_name":"","f211":2,"f985":2,"id":"gkschool291","is_recruitment":1,"is_top":2,"level":2001,"level_name":"普通本科","name":"东莞理工学院","nature":36000,"nature_name":"公办","province_id":44,"province_name":"广东","rank":416,"rank_type":143,"school_id":291,"school_type":6000,"single_province":"","special":[],"type":5001,"type_name":"理工类","view_month":"22.1w","view_month_number":220623,"view_total":"349.7w","view_total_number":3496782,"view_week":"5.7w","view_week_number":56691,"view_year":653238},{"address":"陕西省延安市杨家岭","admissions":2,"answerurl":"","belong":"陕西省","central":2,"city_id":6106,"city_name":"延安市","code_enroll":1071900,"colleges_level":"","county_id":610602,"county_name":"宝塔区","department":2,"doublehigh":0,"dual_class":38003,"dual_class_name":"","f211":2,"f985":2,"id":"gkschool336","is_recruitment":1,"is_top":2,"level":2001,"level_name":"普通本科","name":"延安大学","nature":36000,"nature_name":"公办","province_id":61,"province_name":"陕西","rank":417,"rank_type":116,"school_id":336,"school_type":6000,"single_province":"","special":[],"type":5000,"type_name":"综合类","view_month":"7.8w","view_month_number":78102,"view_total":"349.5w","view_total_number":3494545,"view_week":"1.3w","view_week_number":13176,"view_year":107156},{"address":"临港校区：上海市浦东新区水华路300号,闵行校区：上海市闵行区江川路690号","admissions":2,"answerurl":"https://answer.eol.cn/fillmess/index?id=1552\u0026source=zsgk_app","belong":"上海市","central":2,"city_id":3101,"city_name":"上海市","code_enroll":1145800,"colleges_level":"","county_id":310115,"county_name":"浦东新区","department":2,"doublehigh":0,"dual_class":38003,"dual_class_name":"","f211":2,"f985":2,"id":"gkschool1092","is_recruitment":1,"is_top":2,"level":2001,"level_name":"普通本科","name":"上海电机学院","nature":36000,"nature_name":"公办","province_id":31,"province_name":"上海","rank":418,"rank_type":144,"school_id":1092,"school_type":6000,"single_province":"31","special":[],"type":5001,"type_name":"理工类","view_month":"18.9w","view_month_number":188886,"view_total":"345.5w","view_total_number":3455237,"view_week":"4.1w","view_week_number":40965,"view_year":754389},{"address":"江西省吉安市青原区学苑路28号","admissions":2,"answerurl":"https://answer.eol.cn/fillmess/index?id=768\u0026source=zsgk_app","belong":"江西省","central":2,"city_id":3608,"city_name":"吉安市","code_enroll":1041900,"colleges_level":"","county_id":360803,"county_name":"青原区","department":2,"doublehigh":0,"dual_class":38003,"dual_class_name":"","f211":2,"f985":2,"id":"gkschool197","is_recruitment":1,"is_top":2,"level":2001,"level_name":"普通本科","name":"井冈山大学","nature":36000,"nature_name":"公办","province_id":36,"province_name":"江西","rank":419,"rank_type":117,"school_id":197,"school_type":6000,"single_province":"","special":[],"type":5000,"type_name":"综合类","view_month":"22.8w","view_month_number":228402,"view_total":"345.4w","view_total_number":3454363,"view_week":"6.6w","view_week_number":66315,"view_year":667365}],"numFound":2855},"location":"","encrydata":""}